elfwrapper/__init__.py
elfwrapper/elf_exception.py
elfwrapper/elf_wrapper.py
elfwrapper/utility.py
pyelfwrapper-0.0.6.dist-info/METADATA
pyelfwrapper-0.0.6.dist-info/WHEEL
pyelfwrapper-0.0.6.dist-info/top_level.txt
pyelfwrapper-0.0.6.dist-info/RECORD
