Metadata-Version: 2.1
Name: pyelfwrapper
Version: 0.0.6
Summary: A wrapper for dwarf format elf file
Home-page: https://github.com/sgnes/elf_dwarf_wrapper
Author: Sgnes
Author-email: sgnes0514@gmai.com
Classifier: Programming Language :: Python :: 3
Classifier: License :: OSI Approved :: MIT License
Classifier: Operating System :: OS Independent
Requires-Python: >=3.8
Requires-Dist: pyelftools
